spark_json_flatten/__init__.py
spark_json_flatten/flattener.py
spark_json_flatten-0.1.1.dist-info/licenses/LICENSE
spark_json_flatten-0.1.1.dist-info/METADATA
spark_json_flatten-0.1.1.dist-info/WHEEL
spark_json_flatten-0.1.1.dist-info/top_level.txt
spark_json_flatten-0.1.1.dist-info/RECORD
