Metadata-Version: 2.4
Name: spark-json-flatten
Version: 0.1.1
Summary: Recursively flatten complex PySpark DataFrames with nested structs and arrays
Author: Gaurav Singh Bisht
License: MIT
Classifier: Programming Language :: Python :: 3
Classifier: License :: OSI Approved :: MIT License
Classifier: Topic :: Software Development :: Libraries
Classifier: Topic :: Database
Requires-Python: >=3.8
License-File: LICENSE
Requires-Dist: pyspark>=3.0.0
Provides-Extra: dev
Requires-Dist: pytest; extra == "dev"
Dynamic: license-file
